sctp.py
_sctp.cpython-311-i386-linux-gnu.so
pysctp-0.7.2.data/data/include/_sctp.h
pysctp.libs/libsctp-fc44796d.so.1.0.17
pysctp-0.7.2.dist-info/top_level.txt
pysctp-0.7.2.dist-info/WHEEL
pysctp-0.7.2.dist-info/RECORD
pysctp-0.7.2.dist-info/METADATA
